AUTHORS.rst
CONTRIBUTING.rst
HISTORY.rst
LICENSE
MANIFEST.in
README.rst
setup.cfg
setup.py
arwn/__init__.py
arwn/engine.py
arwn/handlers.py
arwn/temperature.py
arwn.egg-info/PKG-INFO
arwn.egg-info/SOURCES.txt
arwn.egg-info/dependency_links.txt
arwn.egg-info/not-zip-safe
arwn.egg-info/requires.txt
arwn.egg-info/top_level.txt
arwn/cmd/__init__.py
arwn/cmd/collect.py
arwn/vendor/__init__.py
arwn/vendor/RFXtrx/__init__.py
arwn/vendor/RFXtrx/lowlevel.py
arwn/vendor/RFXtrx/pyserial.py
bin/arwn-collect
docs/Makefile
docs/authors.rst
docs/conf.py
docs/contributing.rst
docs/history.rst
docs/index.rst
docs/installation.rst
docs/make.bat
docs/readme.rst
docs/usage.rst
tests/__init__.py
tests/arwn_fixtures.py
tests/test_arwn.py
tests/test_arwn_collect.py
tests/test_handlers.py
tests/test_mqtt_real.py