Metadata-Version: 1.1
Name: arwn
Version: 2.0.0
Summary: Collect 433Mhz weather sensor data and publish to mqtt
Home-page: https://github.com/sdague/arwn
Author: Sean Dague
Author-email: sean@dague.net
License: Apache 2
Keywords: arwn
Platform: UNKNOWN
Classifier: Development Status :: 4 - Beta
Classifier: Intended Audience :: Developers
Classifier: License :: OSI Approved :: Apache Software License
Classifier: Natural Language :: English
Classifier: Programming Language :: Python :: 3
Classifier: Programming Language :: Python :: 3.5
Classifier: Programming Language :: Python :: 3.6
Classifier: Programming Language :: Python :: 3.7
Classifier: Programming Language :: Python :: 3.8
